{"config": {"view": {"continuousWidth": 400, "continuousHeight": 300}, "axis": {"labelFontSize": 11, "titleFontSize": 15}, "axisBottom": {"labelAngle": 60}}, "hconcat": [{"layer": [{"mark": "bar", "encoding": {"color": {"value": "transparent"}, "tooltip": [{"aggregate": "sum", "field": "noisy_count", "title": "noisy count", "type": "quantitative"}, {"aggregate": "sum", "field": "noisy_count_prev", "title": "prev count", "type": "quantitative"}, {"aggregate": "sum", "field": "error", "title": "current error", "type": "quantitative"}, {"aggregate": "sum", "field": "error_prev", "title": "prev error", "type": "quantitative"}], "x": {"field": "income", "sort": null, "title": "Income", "type": "ordinal"}}, "height": 300, "selection": {"selector623": {"type": "interval", "encodings": ["x"]}}, "transform": [{"filter": {"selection": "selector624"}}], "width": 450}, {"mark": {"type": "bar", "color": "gray", "opacity": 0}, "encoding": {"x": {"field": "income", "sort": null, "title": "Income", "type": "ordinal"}, "y": {"aggregate": "sum", "field": "noisy_count_prev", "type": "quantitative"}}, "transform": [{"filter": {"selection": "selector624"}}]}, {"mark": {"type": "bar", "color": "#4C7FFF", "opacity": 0.7}, "encoding": {"x": {"field": "income", "sort": null, "title": "Income", "type": "ordinal"}, "y": {"aggregate": "sum", "field": "noisy_count", "type": "quantitative"}}, "transform": [{"filter": {"selection": "selector624"}}]}, {"mark": {"type": "point", "color": "black", "opacity": 0.7}, "encoding": {"x": {"field": "income", "sort": null, "title": "Income", "type": "ordinal"}, "y": {"aggregate": "sum", "field": "noisy_count", "title": "Noisy Count", "type": "quantitative"}}, "transform": [{"filter": {"selection": "selector624"}}]}, {"mark": {"type": "rule", "color": "#B6B6B6", "size": 2, "strokeDash": [3, 3]}, "encoding": {"x": {"field": "income", "sort": null, "title": "Income", "type": "ordinal"}, "y": {"aggregate": "sum", "field": "plus_error_prev_income", "title": "", "type": "quantitative"}, "y2": {"aggregate": "sum", "field": "minus_error_prev_income", "title": ""}}, "transform": [{"filter": {"selection": "selector624"}}]}, {"mark": {"type": "tick", "color": "#B90000", "size": 0, "strokeDash": [1, 1]}, "encoding": {"x": {"field": "income", "sort": null, "title": "Income", "type": "ordinal"}, "y": {"aggregate": "sum", "field": "plus_error_prev_income", "type": "quantitative"}}, "transform": [{"filter": {"selection": "selector624"}}]}, {"mark": {"type": "tick", "color": "#B90000", "size": 0, "strokeDash": [3, 1]}, "encoding": {"x": {"field": "income", "sort": null, "title": "Income", "type": "ordinal"}, "y": {"aggregate": "sum", "field": "minus_error_prev_income", "type": "quantitative"}}, "transform": [{"filter": {"selection": "selector624"}}]}, {"mark": {"type": "rule", "color": "black", "size": 2}, "encoding": {"x": {"field": "income", "sort": null, "title": "Income", "type": "ordinal"}, "y": {"aggregate": "sum", "field": "plus_error", "title": "", "type": "quantitative"}, "y2": {"aggregate": "sum", "field": "minus_error", "title": ""}}, "transform": [{"filter": {"selection": "selector624"}}]}, {"mark": {"type": "tick", "color": "black", "width": 0}, "encoding": {"x": {"field": "income", "sort": null, "title": "Income", "type": "ordinal"}, "y": {"aggregate": "sum", "field": "plus_error", "type": "quantitative"}}, "transform": [{"filter": {"selection": "selector624"}}]}, {"mark": {"type": "tick", "color": "black", "width": 0}, "encoding": {"x": {"field": "income", "sort": null, "title": "Income", "type": "ordinal"}, "y": {"aggregate": "sum", "field": "minus_error", "type": "quantitative"}}, "transform": [{"filter": {"selection": "selector624"}}]}]}, {"layer": [{"mark": "bar", "encoding": {"color": {"value": "transparent"}, "tooltip": [{"aggregate": "sum", "field": "noisy_count", "title": "noisy count", "type": "quantitative"}, {"aggregate": "sum", "field": "noisy_count_prev", "title": "prev count", "type": "quantitative"}, {"aggregate": "sum", "field": "error", "title": "current error", "type": "quantitative"}, {"aggregate": "sum", "field": "error_prev", "title": "prev error", "type": "quantitative"}], "x": {"field": "race", "sort": null, "title": "Race", "type": "ordinal"}}, "height": 300, "selection": {"selector624": {"type": "interval", "encodings": ["x"]}}, "transform": [{"filter": {"selection": "selector623"}}], "width": 450}, {"mark": {"type": "bar", "color": "gray", "opacity": 0}, "encoding": {"x": {"field": "race", "sort": null, "title": "Race", "type": "ordinal"}, "y": {"aggregate": "sum", "field": "noisy_count_prev", "type": "quantitative"}}, "transform": [{"filter": {"selection": "selector623"}}]}, {"mark": {"type": "bar", "color": "#4C7FFF", "opacity": 0.7}, "encoding": {"x": {"field": "race", "sort": null, "title": "Race", "type": "ordinal"}, "y": {"aggregate": "sum", "field": "noisy_count", "type": "quantitative"}}, "transform": [{"filter": {"selection": "selector623"}}]}, {"mark": {"type": "point", "color": "black", "opacity": 0.7}, "encoding": {"x": {"field": "race", "sort": null, "title": "Race", "type": "ordinal"}, "y": {"aggregate": "sum", "field": "noisy_count", "title": "Noisy Count", "type": "quantitative"}}, "transform": [{"filter": {"selection": "selector623"}}]}, {"mark": {"type": "rule", "color": "#B6B6B6", "size": 2, "strokeDash": [3, 3]}, "encoding": {"x": {"field": "race", "sort": null, "title": "Race", "type": "ordinal"}, "y": {"aggregate": "sum", "field": "plus_error_prev_race", "title": "", "type": "quantitative"}, "y2": {"aggregate": "sum", "field": "minus_error_prev_race", "title": ""}}, "transform": [{"filter": {"selection": "selector623"}}]}, {"mark": {"type": "tick", "color": "#B90000", "size": 0, "strokeDash": [1, 1]}, "encoding": {"x": {"field": "race", "sort": null, "title": "Race", "type": "ordinal"}, "y": {"aggregate": "sum", "field": "plus_error_prev_race", "type": "quantitative"}}, "transform": [{"filter": {"selection": "selector623"}}]}, {"mark": {"type": "tick", "color": "#B90000", "size": 0, "strokeDash": [3, 1]}, "encoding": {"x": {"field": "race", "sort": null, "title": "Race", "type": "ordinal"}, "y": {"aggregate": "sum", "field": "minus_error_prev_race", "type": "quantitative"}}, "transform": [{"filter": {"selection": "selector623"}}]}, {"mark": {"type": "rule", "color": "black", "size": 2}, "encoding": {"x": {"field": "race", "sort": null, "title": "Race", "type": "ordinal"}, "y": {"aggregate": "sum", "field": "plus_error", "title": "", "type": "quantitative"}, "y2": {"aggregate": "sum", "field": "minus_error", "title": ""}}, "transform": [{"filter": {"selection": "selector623"}}]}, {"mark": {"type": "tick", "color": "black", "width": 0}, "encoding": {"x": {"field": "race", "sort": null, "title": "Race", "type": "ordinal"}, "y": {"aggregate": "sum", "field": "plus_error", "type": "quantitative"}}, "transform": [{"filter": {"selection": "selector623"}}]}, {"mark": {"type": "tick", "color": "black", "width": 0}, "encoding": {"x": {"field": "race", "sort": null, "title": "Race", "type": "ordinal"}, "y": {"aggregate": "sum", "field": "minus_error", "type": "quantitative"}}, "transform": [{"filter": {"selection": "selector623"}}]}]}], "data": {"name": "data-c2579acd4946ea3f912f92a877999c35"}, "$schema": "https://vega.github.io/schema/vega-lite/v4.17.0.json", "datasets": {"data-c2579acd4946ea3f912f92a877999c35": [{"income": "$0k - $49k", "race": "White", "noisy_count": 33156.7, "true_count": 33156.0, "plus_error": 33174.7, "minus_error": 33138.6, "error": 18.1, "noisy_count_prev": 33142.8, "true_count_prev": 33156.0, "plus_error_prev": 33165.4, "minus_error_prev": 33120.2, "error_prev": 22.6, "plus_error_prev_income": 33176.275, "minus_error_prev_income": 33131.075, "plus_error_prev_race": 33169.58, "minus_error_prev_race": 33124.38}, {"income": "$0k - $49k", "race": "Black", "noisy_count": 4282.1, "true_count": 4314.0, "plus_error": 4300.1, "minus_error": 4264.0, "error": 18.1, "noisy_count_prev": 4289.2, "true_count_prev": 4314.0, "plus_error_prev": 4311.8, "minus_error_prev": 4266.6, "error_prev": 22.6, "plus_error_prev_income": 4322.675, "minus_error_prev_income": 4277.475, "plus_error_prev_race": 4317.17, "minus_error_prev_race": 4271.97}, {"income": "$0k - $49k", "race": "American Indian", "noisy_count": 507.7, "true_count": 489.0, "plus_error": 525.7, "minus_error": 489.6, "error": 18.1, "noisy_count_prev": 489.9, "true_count_prev": 489.0, "plus_error_prev": 512.5, "minus_error_prev": 467.3, "error_prev": 22.6, "plus_error_prev_income": 523.375, "minus_error_prev_income": 478.175, "plus_error_prev_race": 507.94, "minus_error_prev_race": 462.74}, {"income": "$0k - $49k", "race": "Chinese", "noisy_count": 1038.5, "true_count": 992.0, "plus_error": 1056.6, "minus_error": 1020.4, "error": 18.1, "noisy_count_prev": 1019.6, "true_count_prev": 992.0, "plus_error_prev": 1042.2, "minus_error_prev": 997.0, "error_prev": 22.6, "plus_error_prev_income": 1053.075, "minus_error_prev_income": 1007.875, "plus_error_prev_race": 1043.48, "minus_error_prev_race": 998.28}, {"income": "$50k - $99k", "race": "White", "noisy_count": 7527.0, "true_count": 7572.0, "plus_error": 7556.8, "minus_error": 7497.2, "error": 29.8, "noisy_count_prev": 7549.2, "true_count_prev": 7572.0, "plus_error_prev": 7593.9, "minus_error_prev": 7504.4, "error_prev": 44.7, "plus_error_prev_income": 7587.35, "minus_error_prev_income": 7497.85, "plus_error_prev_race": 7598.079999999999, "minus_error_prev_race": 7508.579999999999}, {"income": "$50k - $99k", "race": "Black", "noisy_count": 515.2, "true_count": 547.0, "plus_error": 545.0, "minus_error": 485.4, "error": 29.8, "noisy_count_prev": 503.5, "true_count_prev": 547.0, "plus_error_prev": 548.2, "minus_error_prev": 458.8, "error_prev": 44.7, "plus_error_prev_income": 541.6500000000003, "minus_error_prev_income": 452.2500000000003, "plus_error_prev_race": 553.5700000000002, "minus_error_prev_race": 464.1700000000001}, {"income": "$50k - $99k", "race": "American Indian", "noisy_count": 18.2, "true_count": 64.0, "plus_error": 48.0, "minus_error": -11.6, "error": 29.8, "noisy_count_prev": 43.4, "true_count_prev": 64.0, "plus_error_prev": 88.1, "minus_error_prev": -1.3, "error_prev": 44.7, "plus_error_prev_income": 81.55000000000027, "minus_error_prev_income": -7.849999999999727, "plus_error_prev_race": 83.53999999999999, "minus_error_prev_race": -5.859999999999997}, {"income": "$50k - $99k", "race": "Chinese", "noisy_count": 328.7, "true_count": 344.0, "plus_error": 358.5, "minus_error": 298.9, "error": 29.8, "noisy_count_prev": 319.2, "true_count_prev": 344.0, "plus_error_prev": 363.9, "minus_error_prev": 274.5, "error_prev": 44.7, "plus_error_prev_income": 357.35000000000025, "minus_error_prev_income": 267.9500000000003, "plus_error_prev_race": 365.17999999999995, "minus_error_prev_race": 275.78}, {"income": "$100k - $149k", "race": "White", "noisy_count": 1006.7, "true_count": 1036.0, "plus_error": 1036.5, "minus_error": 976.9, "error": 29.8, "noisy_count_prev": 955.4, "true_count_prev": 1036.0, "plus_error_prev": 1000.1, "minus_error_prev": 910.6, "error_prev": 44.7, "plus_error_prev_income": 1013.625, "minus_error_prev_income": 924.125, "plus_error_prev_race": 1004.2799999999996, "minus_error_prev_race": 914.7799999999996}, {"income": "$100k - $149k", "race": "Black", "noisy_count": 32.4, "true_count": 45.0, "plus_error": 62.2, "minus_error": 2.6, "error": 29.8, "noisy_count_prev": 55.7, "true_count_prev": 45.0, "plus_error_prev": 100.4, "minus_error_prev": 10.9, "error_prev": 44.7, "plus_error_prev_income": 113.92499999999998, "minus_error_prev_income": 24.424999999999976, "plus_error_prev_race": 105.77000000000008, "minus_error_prev_race": 16.270000000000074}, {"income": "$100k - $149k", "race": "American Indian", "noisy_count": 53.4, "true_count": 4.0, "plus_error": 83.2, "minus_error": 23.6, "error": 29.8, "noisy_count_prev": 36.6, "true_count_prev": 4.0, "plus_error_prev": 81.3, "minus_error_prev": -8.2, "error_prev": 44.7, "plus_error_prev_income": 94.82499999999997, "minus_error_prev_income": 5.324999999999978, "plus_error_prev_race": 76.74, "minus_error_prev_race": -12.759999999999996}, {"income": "$100k - $149k", "race": "Chinese", "noisy_count": 152.5, "true_count": 64.0, "plus_error": 182.3, "minus_error": 122.7, "error": 29.8, "noisy_count_prev": 143.2, "true_count_prev": 64.0, "plus_error_prev": 187.9, "minus_error_prev": 98.5, "error_prev": 44.7, "plus_error_prev_income": 201.42499999999998, "minus_error_prev_income": 112.02499999999998, "plus_error_prev_race": 189.18, "minus_error_prev_race": 99.78}, {"income": "$150k - $199k", "race": "White", "noisy_count": 566.1, "true_count": 559.0, "plus_error": 578.8, "minus_error": 553.4, "error": 12.7, "noisy_count_prev": 563.5, "true_count_prev": 559.0, "plus_error_prev": 585.4, "minus_error_prev": 541.5, "error_prev": 21.9, "plus_error_prev_income": 587.575, "minus_error_prev_income": 543.675, "plus_error_prev_race": 589.5799999999996, "minus_error_prev_race": 545.6799999999996}, {"income": "$150k - $199k", "race": "Black", "noisy_count": -19.8, "true_count": 15.0, "plus_error": -7.1, "minus_error": -32.4, "error": 12.7, "noisy_count_prev": -32.1, "true_count_prev": 15.0, "plus_error_prev": -10.1, "minus_error_prev": -54.0, "error_prev": 21.9, "plus_error_prev_income": -7.924999999999988, "minus_error_prev_income": -51.82499999999999, "plus_error_prev_race": -4.729999999999927, "minus_error_prev_race": -48.629999999999924}, {"income": "$150k - $199k", "race": "American Indian", "noisy_count": 8.9, "true_count": 1.0, "plus_error": 21.6, "minus_error": -3.8, "error": 12.7, "noisy_count_prev": 20.3, "true_count_prev": 1.0, "plus_error_prev": 42.2, "minus_error_prev": -1.6, "error_prev": 21.9, "plus_error_prev_income": 44.375000000000014, "minus_error_prev_income": 0.5750000000000113, "plus_error_prev_race": 37.64000000000001, "minus_error_prev_race": -6.159999999999997}, {"income": "$150k - $199k", "race": "Chinese", "noisy_count": 35.5, "true_count": 34.0, "plus_error": 48.2, "minus_error": 22.8, "error": 12.7, "noisy_count_prev": 30.3, "true_count_prev": 34.0, "plus_error_prev": 52.2, "minus_error_prev": 8.3, "error_prev": 21.9, "plus_error_prev_income": 54.375000000000014, "minus_error_prev_income": 10.475000000000012, "plus_error_prev_race": 53.48, "minus_error_prev_race": 9.579999999999997}, {"income": "$200k - $249k", "race": "White", "noisy_count": 206.9, "true_count": 122.0, "plus_error": 236.7, "minus_error": 177.1, "error": 29.8, "noisy_count_prev": 198.5, "true_count_prev": 122.0, "plus_error_prev": 243.2, "minus_error_prev": 153.8, "error_prev": 44.7, "plus_error_prev_income": 234.575, "minus_error_prev_income": 145.175, "plus_error_prev_race": 247.37999999999954, "minus_error_prev_race": 157.97999999999956}, {"income": "$200k - $249k", "race": "Black", "noisy_count": 9.0, "true_count": 7.0, "plus_error": 38.8, "minus_error": -20.8, "error": 29.8, "noisy_count_prev": 19.5, "true_count_prev": 7.0, "plus_error_prev": 64.2, "minus_error_prev": -25.2, "error_prev": 44.7, "plus_error_prev_income": 55.57500000000001, "minus_error_prev_income": -33.82499999999999, "plus_error_prev_race": 69.57000000000008, "minus_error_prev_race": -19.829999999999927}, {"income": "$200k - $249k", "race": "American Indian", "noisy_count": -19.9, "true_count": 3.0, "plus_error": 9.9, "minus_error": -49.7, "error": 29.8, "noisy_count_prev": -4.4, "true_count_prev": 3.0, "plus_error_prev": 40.3, "minus_error_prev": -49.1, "error_prev": 44.7, "plus_error_prev_income": 31.675000000000004, "minus_error_prev_income": -57.724999999999994, "plus_error_prev_race": 35.74, "minus_error_prev_race": -53.66}, {"income": "$200k - $249k", "race": "Chinese", "noisy_count": -48.4, "true_count": 5.0, "plus_error": -18.6, "minus_error": -78.2, "error": 29.8, "noisy_count_prev": -31.5, "true_count_prev": 5.0, "plus_error_prev": 13.3, "minus_error_prev": -76.2, "error_prev": 44.7, "plus_error_prev_income": 4.675000000000008, "minus_error_prev_income": -84.82499999999999, "plus_error_prev_race": 14.579999999999997, "minus_error_prev_race": -74.92}, {"income": "$250k - $299k", "race": "White", "noisy_count": 58.5, "true_count": 43.0, "plus_error": 71.1, "minus_error": 46.0, "error": 12.6, "noisy_count_prev": 42.8, "true_count_prev": 43.0, "plus_error_prev": 64.4, "minus_error_prev": 21.1, "error_prev": 21.7, "plus_error_prev_income": 69.80000000000001, "minus_error_prev_income": 26.5, "plus_error_prev_race": 68.57999999999957, "minus_error_prev_race": 25.279999999999564}, {"income": "$250k - $299k", "race": "Black", "noisy_count": 7.3, "true_count": 0.0, "plus_error": 19.9, "minus_error": -5.2, "error": 12.6, "noisy_count_prev": -10.0, "true_count_prev": 0.0, "plus_error_prev": 11.7, "minus_error_prev": -31.7, "error_prev": 21.7, "plus_error_prev_income": 17.099999999999998, "minus_error_prev_income": -26.3, "plus_error_prev_race": 17.07000000000007, "minus_error_prev_race": -26.329999999999927}, {"income": "$250k - $299k", "race": "American Indian", "noisy_count": -50.9, "true_count": 0.0, "plus_error": -38.3, "minus_error": -63.4, "error": 12.6, "noisy_count_prev": -52.8, "true_count_prev": 0.0, "plus_error_prev": -31.1, "minus_error_prev": -74.5, "error_prev": 21.7, "plus_error_prev_income": -25.700000000000003, "minus_error_prev_income": -69.1, "plus_error_prev_race": -35.66, "minus_error_prev_race": -79.06}, {"income": "$250k - $299k", "race": "Chinese", "noisy_count": 5.9, "true_count": 3.0, "plus_error": 18.5, "minus_error": -6.7, "error": 12.6, "noisy_count_prev": 19.2, "true_count_prev": 3.0, "plus_error_prev": 40.8, "minus_error_prev": -2.5, "error_prev": 21.7, "plus_error_prev_income": 46.199999999999996, "minus_error_prev_income": 2.8999999999999995, "plus_error_prev_race": 42.07999999999999, "minus_error_prev_race": -1.2200000000000046}, {"income": "$300k - $349k", "race": "White", "noisy_count": -32.3, "true_count": 11.0, "plus_error": -2.5, "minus_error": -62.1, "error": 29.8, "noisy_count_prev": -32.9, "true_count_prev": 11.0, "plus_error_prev": 11.8, "minus_error_prev": -77.6, "error_prev": 44.7, "plus_error_prev_income": -4.225000000000005, "minus_error_prev_income": -93.625, "plus_error_prev_race": 15.979999999999563, "minus_error_prev_race": -73.42000000000043}, {"income": "$300k - $349k", "race": "Black", "noisy_count": -21.0, "true_count": 1.0, "plus_error": 8.8, "minus_error": -50.8, "error": 29.8, "noisy_count_prev": 3.0, "true_count_prev": 1.0, "plus_error_prev": 47.7, "minus_error_prev": -41.7, "error_prev": 44.7, "plus_error_prev_income": 31.674999999999997, "minus_error_prev_income": -57.72500000000001, "plus_error_prev_race": 53.07000000000008, "minus_error_prev_race": -36.32999999999993}, {"income": "$300k - $349k", "race": "American Indian", "noisy_count": -128.5, "true_count": 0.0, "plus_error": -98.7, "minus_error": -158.4, "error": 29.8, "noisy_count_prev": -101.8, "true_count_prev": 0.0, "plus_error_prev": -57.1, "minus_error_prev": -146.5, "error_prev": 44.7, "plus_error_prev_income": -73.125, "minus_error_prev_income": -162.525, "plus_error_prev_race": -61.66, "minus_error_prev_race": -151.06}, {"income": "$300k - $349k", "race": "Chinese", "noisy_count": -57.8, "true_count": 0.0, "plus_error": -28.0, "minus_error": -87.6, "error": 29.8, "noisy_count_prev": -43.8, "true_count_prev": 0.0, "plus_error_prev": 0.9, "minus_error_prev": -88.5, "error_prev": 44.7, "plus_error_prev_income": -15.125000000000005, "minus_error_prev_income": -104.525, "plus_error_prev_race": 2.1799999999999953, "minus_error_prev_race": -87.22}, {"income": "$350k - $399k", "race": "White", "noisy_count": 25.0, "true_count": 2.0, "plus_error": 43.0, "minus_error": 7.0, "error": 18.0, "noisy_count_prev": 18.3, "true_count_prev": 2.0, "plus_error_prev": 40.8, "minus_error_prev": -4.2, "error_prev": 22.5, "plus_error_prev_income": 47.9, "minus_error_prev_income": 2.8999999999999995, "plus_error_prev_race": 44.97999999999956, "minus_error_prev_race": -0.020000000000436557}, {"income": "$350k - $399k", "race": "Black", "noisy_count": -15.0, "true_count": 0.0, "plus_error": 3.0, "minus_error": -32.9, "error": 18.0, "noisy_count_prev": -18.1, "true_count_prev": 0.0, "plus_error_prev": 4.4, "minus_error_prev": -40.6, "error_prev": 22.5, "plus_error_prev_income": 11.5, "minus_error_prev_income": -33.5, "plus_error_prev_race": 9.770000000000074, "minus_error_prev_race": -35.229999999999926}, {"income": "$350k - $399k", "race": "American Indian", "noisy_count": -46.5, "true_count": 0.0, "plus_error": -28.5, "minus_error": -64.5, "error": 18.0, "noisy_count_prev": -67.2, "true_count_prev": 0.0, "plus_error_prev": -44.7, "minus_error_prev": -89.7, "error_prev": 22.5, "plus_error_prev_income": -37.6, "minus_error_prev_income": -82.60000000000001, "plus_error_prev_race": -49.26, "minus_error_prev_race": -94.26}, {"income": "$350k - $399k", "race": "Chinese", "noisy_count": 4.5, "true_count": 0.0, "plus_error": 22.5, "minus_error": -13.5, "error": 18.0, "noisy_count_prev": 6.6, "true_count_prev": 0.0, "plus_error_prev": 29.1, "minus_error_prev": -15.9, "error_prev": 22.5, "plus_error_prev_income": 36.2, "minus_error_prev_income": -8.8, "plus_error_prev_race": 30.379999999999995, "minus_error_prev_race": -14.620000000000005}, {"income": "$400k - $449k", "race": "White", "noisy_count": -5.0, "true_count": 2.0, "plus_error": 13.2, "minus_error": -23.2, "error": 18.2, "noisy_count_prev": 9.1, "true_count_prev": 2.0, "plus_error_prev": 32.0, "minus_error_prev": -13.8, "error_prev": 22.9, "plus_error_prev_income": 32.2, "minus_error_prev_income": -13.600000000000001, "plus_error_prev_race": 36.179999999999566, "minus_error_prev_race": -9.620000000000438}, {"income": "$400k - $449k", "race": "Black", "noisy_count": 79.5, "true_count": 0.0, "plus_error": 97.7, "minus_error": 61.2, "error": 18.2, "noisy_count_prev": 46.5, "true_count_prev": 0.0, "plus_error_prev": 69.4, "minus_error_prev": 23.5, "error_prev": 22.9, "plus_error_prev_income": 69.60000000000001, "minus_error_prev_income": 23.7, "plus_error_prev_race": 74.77000000000008, "minus_error_prev_race": 28.870000000000072}, {"income": "$400k - $449k", "race": "American Indian", "noisy_count": -55.1, "true_count": 0.0, "plus_error": -36.8, "minus_error": -73.3, "error": 18.2, "noisy_count_prev": -37.6, "true_count_prev": 0.0, "plus_error_prev": -14.7, "minus_error_prev": -60.5, "error_prev": 22.9, "plus_error_prev_income": -14.5, "minus_error_prev_income": -60.3, "plus_error_prev_race": -19.259999999999998, "minus_error_prev_race": -65.06}, {"income": "$400k - $449k", "race": "Chinese", "noisy_count": 29.5, "true_count": 0.0, "plus_error": 47.8, "minus_error": 11.3, "error": 18.2, "noisy_count_prev": 30.1, "true_count_prev": 0.0, "plus_error_prev": 53.0, "minus_error_prev": 7.1, "error_prev": 22.9, "plus_error_prev_income": 53.2, "minus_error_prev_income": 7.299999999999999, "plus_error_prev_race": 54.279999999999994, "minus_error_prev_race": 8.379999999999995}, {"income": "$450k - $499k", "race": "White", "noisy_count": -60.4, "true_count": 1.0, "plus_error": -30.6, "minus_error": -90.3, "error": 29.8, "noisy_count_prev": -39.3, "true_count_prev": 1.0, "plus_error_prev": 5.4, "minus_error_prev": -84.0, "error_prev": 44.7, "plus_error_prev_income": 13.000000000000002, "minus_error_prev_income": -76.4, "plus_error_prev_race": 9.579999999999565, "minus_error_prev_race": -79.82000000000043}, {"income": "$450k - $499k", "race": "Black", "noisy_count": 42.0, "true_count": 0.0, "plus_error": 71.8, "minus_error": 12.2, "error": 29.8, "noisy_count_prev": 0.8, "true_count_prev": 0.0, "plus_error_prev": 45.6, "minus_error_prev": -43.9, "error_prev": 44.7, "plus_error_prev_income": 53.2, "minus_error_prev_income": -36.3, "plus_error_prev_race": 50.97000000000008, "minus_error_prev_race": -38.52999999999992}, {"income": "$450k - $499k", "race": "American Indian", "noisy_count": 36.4, "true_count": 0.0, "plus_error": 66.2, "minus_error": 6.5, "error": 29.8, "noisy_count_prev": 42.9, "true_count_prev": 0.0, "plus_error_prev": 87.6, "minus_error_prev": -1.8, "error_prev": 44.7, "plus_error_prev_income": 95.19999999999999, "minus_error_prev_income": 5.800000000000002, "plus_error_prev_race": 83.03999999999999, "minus_error_prev_race": -6.359999999999997}, {"income": "$450k - $499k", "race": "Chinese", "noisy_count": 133.8, "true_count": 0.0, "plus_error": 163.6, "minus_error": 104.0, "error": 29.8, "noisy_count_prev": 117.0, "true_count_prev": 0.0, "plus_error_prev": 161.8, "minus_error_prev": 72.3, "error_prev": 44.7, "plus_error_prev_income": 169.4, "minus_error_prev_income": 79.9, "plus_error_prev_race": 163.08, "minus_error_prev_race": 73.58}]}}